MANIFEST.in
README
setup.py
FormatTransformer/TestGenericInput.py
FormatTransformer/TransformManager.py
FormatTransformer/__init__.py
FormatTransformer/create_test_file.py
FormatTransformer/create_test_images.py
FormatTransformer/full_demo_1.0.dic
FormatTransformer/FormatAdapters/__init__.py
FormatTransformer/FormatAdapters/cif_format_adapter.py
FormatTransformer/FormatAdapters/nx_format_adapter.py
FormatTransformer/testfiles/Cu033V2O5_1_001.cbf
FormatTransformer/testfiles/adsc_jrh_testfile.cif
FormatTransformer/testfiles/multi-image-test.cif
FormatTransformer/testfiles/nexus-multi-image.nx
PyFormatTransformer.egg-info/PKG-INFO
PyFormatTransformer.egg-info/SOURCES.txt
PyFormatTransformer.egg-info/dependency_links.txt
PyFormatTransformer.egg-info/requires.txt
PyFormatTransformer.egg-info/top_level.txt