Metadata-Version: 1.1
Name: PyFormatTransformer
Version: 0.5
Summary: Scientific Data Format Transformation Framework
Home-page: UNKNOWN
Author: James Hester
Author-email: jamesrhester at gmail.com
License: GPL
Platform: UNKNOWN
Classifier: Development Status :: 1
Classifier: Environment :: Console
Classifier: Intended Audience :: Developers
Classifier: Intended Audience :: Science/Research
Classifier: Operating System :: OS Independent
Classifier: Programming Language :: Python :: 2
Classifier: Topic :: Scientific/Engineering :: Bio-Informatics
